chora_compose/__init__.py
chora_compose/cli/__init__.py
chora_compose/collaboration/__init__.py
chora_compose/core/__init__.py
chora_compose/core/composer.py
chora_compose/core/config_loader.py
chora_compose/core/context_resolver.py
chora_compose/core/data_selector.py
chora_compose/core/models.py
chora_compose/generators/__init__.py
chora_compose/generators/base.py
chora_compose/generators/bdd_scenario.py
chora_compose/generators/code_generation.py
chora_compose/generators/demonstration.py
chora_compose/generators/jinja2.py
chora_compose/generators/registry.py
chora_compose/generators/template_fill.py
chora_compose/mcp/__init__.py
chora_compose/mcp/config_tools.py
chora_compose/mcp/errors.py
chora_compose/mcp/instance.py
chora_compose/mcp/namespace.py
chora_compose/mcp/resource_providers.py
chora_compose/mcp/resources/__init__.py
chora_compose/mcp/resources/capabilities.py
chora_compose/mcp/server.py
chora_compose/mcp/tools.py
chora_compose/mcp/types.py
chora_compose/mcp/utils.py
chora_compose/models/__init__.py
chora_compose/models/upstream_dependencies.py
chora_compose/storage/__init__.py
chora_compose/storage/ephemeral.py
chora_compose/storage/ephemeral_config.py
chora_compose/telemetry/__init__.py
chora_compose/telemetry/event_emitter.py
chora_compose/telemetry/event_schemas.py
chora_compose/validation/__init__.py
chora_compose/validators/__init__.py
chora_compose-1.8.0.dist-info/METADATA
chora_compose-1.8.0.dist-info/WHEEL
chora_compose-1.8.0.dist-info/licenses/LICENSE
chora_compose-1.8.0.dist-info/RECORD
