Metadata-Version: 2.4
Name: chora-compose
Version: 1.8.0
Summary: Chora Compose - Configuration-driven framework for composing artifacts from structured content
License-File: LICENSE
Author: Victor
Author-email: vlct0r@protonmail.com
Requires-Python: >=3.12,<4.0
Classifier: Programming Language :: Python :: 3
Classifier: Programming Language :: Python :: 3.12
Classifier: Programming Language :: Python :: 3.13
Classifier: Programming Language :: Python :: 3.14
Requires-Dist: anthropic (>=0.69.0,<0.70.0)
Requires-Dist: fastmcp (>=2.12.4,<3.0.0)
Requires-Dist: jinja2 (>=3.1.0,<4.0.0)
Requires-Dist: jsonpath-ng (>=1.7.0,<2.0.0)
Requires-Dist: jsonschema (>=4.20.0,<5.0.0)
Requires-Dist: mcp (>=1.18.0,<2.0.0)
Requires-Dist: pydantic (>=2.0.0,<3.0.0)
Requires-Dist: typer (>=0.19.2,<0.20.0)
